MANIFEST.in
README.txt
plonetheme.portaltwodotoh-configure.zcml
setup.cfg
setup.py
dist/plonetheme.portaltwodotoh-1.3.2-py2.4.egg
docs/HISTORY.txt
docs/INSTALL.txt
docs/LICENSE.GPL
docs/LICENSE.txt
plonetheme/__init__.py
plonetheme.portaltwodotoh.egg-info/PKG-INFO
plonetheme.portaltwodotoh.egg-info/SOURCES.txt
plonetheme.portaltwodotoh.egg-info/dependency_links.txt
plonetheme.portaltwodotoh.egg-info/entry_points.txt
plonetheme.portaltwodotoh.egg-info/namespace_packages.txt
plonetheme.portaltwodotoh.egg-info/not-zip-safe
plonetheme.portaltwodotoh.egg-info/paster_plugins.txt
plonetheme.portaltwodotoh.egg-info/requires.txt
plonetheme.portaltwodotoh.egg-info/top_level.txt
plonetheme/portaltwodotoh/__init__.py
plonetheme/portaltwodotoh/configure.zcml
plonetheme/portaltwodotoh/profiles.zcml
plonetheme/portaltwodotoh/setuphandlers.py
plonetheme/portaltwodotoh/skins.zcml
plonetheme/portaltwodotoh/tests.py
plonetheme/portaltwodotoh/version.txt
plonetheme/portaltwodotoh/Extensions/Install.py
plonetheme/portaltwodotoh/browser/__init__.py
plonetheme/portaltwodotoh/browser/configure.zcml
plonetheme/portaltwodotoh/browser/interfaces.py
plonetheme/portaltwodotoh/browser/viewlet.pt
plonetheme/portaltwodotoh/browser/viewlets.py
plonetheme/portaltwodotoh/browser/images/README.txt
plonetheme/portaltwodotoh/browser/stylesheets/README.txt
plonetheme/portaltwodotoh/browser/stylesheets/main.css
plonetheme/portaltwodotoh/profiles/default/cssregistry.xml
plonetheme/portaltwodotoh/profiles/default/import_steps.xml
plonetheme/portaltwodotoh/profiles/default/jsregistry.xml
plonetheme/portaltwodotoh/profiles/default/metadata.xml
plonetheme/portaltwodotoh/profiles/default/plonetheme.portaltwodotoh_various.txt
plonetheme/portaltwodotoh/profiles/default/skins.xml
plonetheme/portaltwodotoh/profiles/default/viewlets.xml
plonetheme/portaltwodotoh/profiles/uninstall/skins.xml
plonetheme/portaltwodotoh/profiles/uninstall/viewlets.xml
plonetheme/portaltwodotoh/skins/plonetheme_portaltwodotoh_custom_images/CONTENT.txt
plonetheme/portaltwodotoh/skins/plonetheme_portaltwodotoh_custom_images/events_portlet_icon.png
plonetheme/portaltwodotoh/skins/plonetheme_portaltwodotoh_custom_images/link_icon.gif
plonetheme/portaltwodotoh/skins/plonetheme_portaltwodotoh_custom_images/lock_icon.gif
plonetheme/portaltwodotoh/skins/plonetheme_portaltwodotoh_custom_images/logon_portlet_icon.png
