Metadata-Version: 1.0
Name: plonetheme.portaltwodotoh
Version: 1.3.2
Summary: An elastic lounded corners.
Home-page: http://svn.plone.org/svn/collective/plonetheme.portaltwodotoh/
Author: Daniel Kvaternik
Author-email: dkvaternik@nngov.com
License: GPL
Keywords: web zope plone theme
Platform: UNKNOWN
Classifier: Framework :: Plone
Classifier: Programming Language :: Python
Classifier: Topic :: Software Development :: Libraries :: Python Modules
